torch_dct/__init__.py
torch_dct/_dct.py
torch_dct-0.1.6.dist-info/LICENSE
torch_dct-0.1.6.dist-info/METADATA
torch_dct-0.1.6.dist-info/WHEEL
torch_dct-0.1.6.dist-info/top_level.txt
torch_dct-0.1.6.dist-info/RECORD
