Metadata-Version: 2.1
Name: torch-dct
Version: 0.1.6
Summary: Discrete Cosine Transform (DCT) for pytorch
Home-page: https://github.com/zh217/torch-dct
Author: Ziyang Hu
Author-email: hu.ziyang@cantab.net
License: MIT
Platform: any
Classifier: Development Status :: 4 - Beta
Classifier: License :: OSI Approved :: Apache Software License
Classifier: Programming Language :: Python :: 2
Classifier: Programming Language :: Python :: 3
License-File: LICENSE
Requires-Dist: torch (>=0.4.1)
